{
  "miniprogramRoot": "miniprogram/",
  "cloudfunctionRoot": "cloudfunctions/",
  "setting": {
    "urlCheck": true,
    "es6": true,
    "enhance": true,
    "postcss": true,
    "preloadBackgroundData": false,
    "minified": true,
    "newFeature": false,
    "coverView": true,
    "nodeModules": false,
    "autoAudits": false,
    "showShadowRootInWxmlPanel": true,
    "scopeDataCheck": false,
    "uglifyFileName": false,
    "checkInvalidKey": true,
    "checkSiteMap": true,
    "uploadWithSourceMap": true,
    "compileHotReLoad": false,
    "lazyloadPlaceholderEnable": false,
    "useMultiFrameRuntime": true,
    "useApiHook": true,
    "useApiHostProcess": true
  },
  "appid": "wx123456789012345",
  "projectname": "xiangqi_wechat",
  "libVersion": "2.19.4",
  "cloudfunctionTemplateRoot": "cloudfunctionTemplate",
  "condition": {
    "search": {
      "list": []
    },
    "conversation": {
      "list": []
    },
    "plugin": {
      "list": []
    },
    "game": {
      "list": []
    },
    "miniprogram": {
      "list": []
    }
  }
}
